fluster_py/__init__.py
fluster_py/core/__init__.py
fluster_py/core/static/__init__.py
fluster_py/core/static/database_tables.py
fluster_py/features/__init__.py
fluster_py/features/db/__init__.py
fluster_py/features/db/methods/__init__.py
fluster_py/features/db/methods/get_table.py
fluster_py/features/mdx/__init__.py
fluster_py/features/mdx/methods/__init__.py
fluster_py-0.1.5.dist-info/WHEEL
fluster_py-0.1.5.dist-info/METADATA
fluster_py-0.1.5.dist-info/RECORD
