Metadata-Version: 2.3
Name: fluster-py
Version: 0.1.5
Summary: The python API for the Fluster note taking ecosystem.
Author: Fluster.IO
Author-email: Fluster.IO <uhlittlelessdumb@gmail.com>
Requires-Dist: appdirs>=1.4.4
Requires-Dist: lancedb>=0.25.2
Requires-Dist: langchain-community>=0.4
Requires-Dist: langchain-text-splitters>=1.0.0
Requires-Dist: ollama>=0.6.0
Requires-Dist: pypdf>=6.1.2
Requires-Python: >=3.11
